haskellian/either/__init__.py
haskellian/either/funcs.py
haskellian/either/narrowing.py
haskellian/either/type.py
haskellian/either/extras/__init__.py
haskellian/either/extras/pydantic.py
haskellian_either-0.1.9.dist-info/METADATA
haskellian_either-0.1.9.dist-info/WHEEL
haskellian_either-0.1.9.dist-info/top_level.txt
haskellian_either-0.1.9.dist-info/RECORD
