Metadata-Version: 2.1
Name: haskellian-either
Version: 0.1.9
Summary: Simple Either type
Author-email: Marcel Claramunt <marcel@moveread.com>
Requires-Python: >=3.10
Provides-Extra: pydantic
Requires-Dist: pydantic ; extra == 'pydantic'
